{
	"fields": [
		{
			"name": "name",
			"position": 0,
			"type": "String",
			"write_method": "writeUTF"
		},
		{
			"is_vector": true,
			"name": "colors",
			"position": 4,
			"type": "int",
			"write_length_method": "writeShort",
			"write_method": "writeInt"
		},
		{
			"default_value": "0",
			"name": "breed",
			"position": 1,
			"type": "int",
			"write_method": "writeByte"
		},
		{
			"default_value": "false",
			"name": "sex",
			"position": 2,
			"type": "Boolean",
			"write_method": "writeBoolean"
		},
		{
			"bounds": {
				"low": "0"
			},
			"default_value": "0",
			"name": "cosmeticId",
			"position": 3,
			"type": "uint",
			"write_method": "writeVarShort"
		}
	],
	"name": "CharacterRemodelingInformation",
	"namespace": "com.ankamagames.dofus.network.types.game.character.choice",
	"protocolID": 9208,
	"super": "AbstractCharacterInformation",
	"super_serialize": true,
	"supernamespace": "com.ankamagames.dofus.network.types.game.character",
	"use_hash_function": false
}